{
  "name": "cpservices-pricing",
  "displayName": "Pricing service",
  "description": "Pricing service",
  "icon": "https://digitalmarketplace-sapcpprd.s3.eu-central-1.amazonaws.com/26wnPGhAy5d_fjczf2bqoKjQefFEMlzW8HbcYcUIOaaPTqabx6YqSj3bFEWaaN8t.svg",
  "servicePlans": [
    {
      "name": "commerce",
      "displayName": "commerce",
      "category": "SERVICE",
      "description": "for SAP Commerce integration",
      "isFree": null,
      "isBeta": false,
      "dataCenters": [
        {
          "region": "ap11",
          "name": "cf-ap11"
        },
        {
          "region": "eu10",
          "name": "cf-eu10"
        },
        {
          "region": "eu20",
          "name": "cf-eu20"
        },
        {
          "region": "us10",
          "name": "cf-us10"
        }
      ],
      "materialNumberMapping": [
        {
          "materialNumber": "8005695",
          "commercialModel": "Subscription"
        }
      ]
    },
    {
      "name": "cpq",
      "displayName": "cpq",
      "category": "SERVICE",
      "description": "for SAP CPQ integration",
      "isFree": null,
      "isBeta": false,
      "dataCenters": [
        {
          "region": "ap11",
          "name": "cf-ap11"
        },
        {
          "region": "eu10",
          "name": "cf-eu10"
        },
        {
          "region": "eu20",
          "name": "cf-eu20"
        },
        {
          "region": "us10",
          "name": "cf-us10"
        }
      ],
      "materialNumberMapping": [
        {
          "materialNumber": "8007056",
          "commercialModel": "Subscription"
        },
        {
          "materialNumber": "8007057",
          "commercialModel": "Subscription"
        },
        {
          "materialNumber": "8008154",
          "commercialModel": "Subscription"
        },
        {
          "materialNumber": "8008501",
          "commercialModel": "Subscription"
        },
        {
          "materialNumber": "8008503",
          "commercialModel": "Subscription"
        }
      ]
    },
    {
      "name": "cps-prod",
      "displayName": "cps-prod",
      "category": "SERVICE",
      "description": "Productive tenant, one tenant per backend client needed, one subaccount per tenant with Cloud Foundry enabled",
      "isFree": null,
      "isBeta": false,
      "dataCenters": [
        {
          "region": "ap11",
          "name": "cf-ap11"
        },
        {
          "region": "eu10",
          "name": "cf-eu10"
        },
        {
          "region": "eu11",
          "name": "cf-eu11"
        },
        {
          "region": "eu20",
          "name": "cf-eu20"
        },
        {
          "region": "us10",
          "name": "cf-us10"
        }
      ],
      "materialNumberMapping": [
        {
          "materialNumber": "8005772",
          "commercialModel": "Subscription"
        },
        {
          "materialNumber": "8006356",
          "commercialModel": "Subscription"
        },
        {
          "materialNumber": "8011539",
          "commercialModel": "Subscription"
        },
        {
          "materialNumber": "8011539",
          "commercialModel": "Subscription"
        },
        {
          "materialNumber": "8011540",
          "commercialModel": "Subscription"
        },
        {
          "materialNumber": "8015476",
          "commercialModel": "Subscription"
        },
        {
          "materialNumber": "8015503",
          "commercialModel": "Subscription"
        },
        {
          "materialNumber": "8015612",
          "commercialModel": "Subscription"
        },
        {
          "materialNumber": "8015613",
          "commercialModel": "Subscription"
        }
      ]
    },
    {
      "name": "cps-test",
      "displayName": "cps-test",
      "category": "SERVICE",
      "description": "Non-productive tenant, one tenant per backend client needed, one subaccount per tenant with Cloud Foundry enabled",
      "isFree": null,
      "isBeta": false,
      "dataCenters": [
        {
          "region": "ap11",
          "name": "cf-ap11"
        },
        {
          "region": "eu10",
          "name": "cf-eu10"
        },
        {
          "region": "eu11",
          "name": "cf-eu11"
        },
        {
          "region": "eu20",
          "name": "cf-eu20"
        },
        {
          "region": "us10",
          "name": "cf-us10"
        }
      ],
      "materialNumberMapping": [
        {
          "materialNumber": "8005772",
          "commercialModel": "Subscription"
        },
        {
          "materialNumber": "8006356",
          "commercialModel": "Subscription"
        },
        {
          "materialNumber": "8011539",
          "commercialModel": "Subscription"
        },
        {
          "materialNumber": "8011540",
          "commercialModel": "Subscription"
        },
        {
          "materialNumber": "8011540",
          "commercialModel": "Subscription"
        },
        {
          "materialNumber": "8015462",
          "commercialModel": "Subscription"
        },
        {
          "materialNumber": "8015476",
          "commercialModel": "Subscription"
        },
        {
          "materialNumber": "8015503",
          "commercialModel": "Subscription"
        },
        {
          "materialNumber": "8015612",
          "commercialModel": "Subscription"
        },
        {
          "materialNumber": "8015613",
          "commercialModel": "Subscription"
        }
      ]
    },
    {
      "name": "default",
      "displayName": "default",
      "category": "SERVICE",
      "description": "Pricing service",
      "isFree": null,
      "isBeta": false,
      "dataCenters": [
        {
          "region": "ap11",
          "name": "cf-ap11"
        },
        {
          "region": "eu10",
          "name": "cf-eu10"
        },
        {
          "region": "eu20",
          "name": "cf-eu20"
        },
        {
          "region": "us10",
          "name": "cf-us10"
        }
      ],
      "materialNumberMapping": [
        {
          "materialNumber": "8005772",
          "commercialModel": "Subscription"
        },
        {
          "materialNumber": "8005772",
          "commercialModel": "Subscription"
        },
        {
          "materialNumber": "8006356",
          "commercialModel": "Subscription"
        },
        {
          "materialNumber": "8006356",
          "commercialModel": "Subscription"
        },
        {
          "materialNumber": "8011539",
          "commercialModel": "Subscription"
        },
        {
          "materialNumber": "8011540",
          "commercialModel": "Subscription"
        },
        {
          "materialNumber": "8015612",
          "commercialModel": "Subscription"
        },
        {
          "materialNumber": "8015613",
          "commercialModel": "Subscription"
        }
      ]
    },
    {
      "name": "partner",
      "displayName": "partner",
      "category": "SERVICE",
      "description": "Non-productive tenant, for test & demo, one tenant per backend client needed, one subaccount per tenant with Cloud Foundry enabled",
      "isFree": null,
      "isBeta": false,
      "dataCenters": [
        {
          "region": "ap11",
          "name": "cf-ap11"
        },
        {
          "region": "eu10",
          "name": "cf-eu10"
        },
        {
          "region": "eu20",
          "name": "cf-eu20"
        },
        {
          "region": "us10",
          "name": "cf-us10"
        }
      ],
      "materialNumberMapping": [
        {
          "materialNumber": "8014901",
          "commercialModel": "Subscription"
        }
      ]
    }
  ],
  "certifications": []
}