{
  "name": "euporie",
  "displayName": "euporie",
  "description": "Tenant lifecycle orchestration service used by Deploy with Confidence.",
  "icon": null,
  "servicePlans": [
    {
      "name": "default",
      "displayName": "default",
      "category": "SERVICE",
      "description": "Default plan",
      "isFree": true,
      "isBeta": false,
      "dataCenters": [
        {
          "region": "eu10",
          "name": "Europe (Frankfurt)"
        },
        {
          "region": "eu20",
          "name": "Europe (Netherlands)"
        }
      ],
      "materialNumberMappings": []
    }
  ],
  "certifications": []
}