{
  "name": "personal-data-manager-service",
  "displayName": "SAP Personal Data Manager",
  "description": "SAP Personal Data Manager provides the capability to generate reports showing the personal data stored in an application point of view with the help of a CSR. The reports can be generated and exported either in machine readable form (JSON) or human readable form (PDF). Data subjects can request the correction and deletion of personal data that is stored in an application point of view.",
  "icon": "https://digitalmarketplace-sapcpprd.s3.eu-central-1.amazonaws.com/uUrOrPIBknhf8h7-SQkvnzgFaymU7GsT-XHnDA5K1EgUtqKvvEB2Fymn_cYp12fJ.svg",
  "servicePlans": [
    {
      "name": "free",
      "displayName": "free",
      "category": "SERVICE",
      "description": "Free plan. Please note, only community support is available for free service plans and these are not subject to SLAs. Use of free tier service plans are subject to additional terms and conditions as provided in the Business Technology Platform Supplemental Terms and Conditions linked in the Additional Links tab displayed in the Service tile.",
      "isFree": true,
      "isBeta": false,
      "dataCenters": [
        {
          "region": "ap10",
          "name": "Australia (Sydney)"
        },
        {
          "region": "ap11",
          "name": "Singapore"
        },
        {
          "region": "br10",
          "name": "Brazil (Sao Paulo)"
        },
        {
          "region": "eu10",
          "name": "Europe (Frankfurt)"
        },
        {
          "region": "eu11",
          "name": "Europe (Frankfurt) EU Access - AWS"
        },
        {
          "region": "eu20",
          "name": "Europe (Netherlands)"
        },
        {
          "region": "eu30",
          "name": "Europe (Frankfurt)"
        },
        {
          "region": "us10",
          "name": "US East (VA)"
        },
        {
          "region": "us20",
          "name": "US West (WA)"
        },
        {
          "region": "us21",
          "name": "US East (VA)"
        },
        {
          "region": "us30",
          "name": "US Central (IA)"
        }
      ],
      "materialNumberMappings": [
        {
          "materialNumber": "8011149"
        }
      ]
    },
    {
      "name": "standard",
      "displayName": "standard",
      "category": "SERVICE",
      "description": "Standard Plan",
      "isFree": true,
      "isBeta": false,
      "dataCenters": [
        {
          "region": "ap10",
          "name": "Australia (Sydney)"
        },
        {
          "region": "ap11",
          "name": "Singapore"
        },
        {
          "region": "br10",
          "name": "Brazil (Sao Paulo)"
        },
        {
          "region": "eu10",
          "name": "Europe (Frankfurt)"
        },
        {
          "region": "eu11",
          "name": "Europe (Frankfurt) EU Access - AWS"
        },
        {
          "region": "eu20",
          "name": "Europe (Netherlands)"
        },
        {
          "region": "eu30",
          "name": "Europe (Frankfurt)"
        },
        {
          "region": "us10",
          "name": "US East (VA)"
        },
        {
          "region": "us20",
          "name": "US West (WA)"
        },
        {
          "region": "us21",
          "name": "US East (VA)"
        },
        {
          "region": "us30",
          "name": "US Central (IA)"
        }
      ],
      "materialNumberMappings": [
        {
          "materialNumber": "8008848"
        },
        {
          "materialNumber": "8008851"
        }
      ]
    }
  ],
  "certifications": [
    "C5",
    "ISO 22301",
    "ISO 27001",
    "ISO 27017",
    "ISO 27018",
    "SOC 1",
    "SOC 2"
  ]
}